{
  "definitions" : {
    "bypass" : {
      "type" : "object",
      "properties" : {
        "name" : {
          "$ref" : "../core.yaml#/definitions/loc_reference"
        },
        "is_pathfind" : {
          "$ref" : "../core.yaml#/definitions/boolean"
        },
        "use_action" : {
          "$ref" : "../core.yaml#/definitions/boolean"
        },
        "always_active" : {
          "$ref" : "../core.yaml#/definitions/boolean"
        },
        "windup_time" : {
          "$ref" : "../core.yaml#/definitions/int"
        },
        "winddown_time" : {
          "$ref" : "../core.yaml#/definitions/int"
        },
        "ftl_multiplier" : {
          "$ref" : "../core.yaml#/definitions/int"
        },
        "extends_sensors" : {
          "$ref" : "../core.yaml#/definitions/boolean"
        },
        "icon_frame" : {
          "$ref" : "../core.yaml#/definitions/int"
        },
        "remember_instances" : {
          "$ref" : "../core.yaml#/definitions/boolean"
        },
        "galactic_map_tooltip_header" : {
          "$ref" : "../core.yaml#/definitions/loc_reference"
        },
        "galactic_map_tooltip_desc" : {
          "$ref" : "../core.yaml#/definitions/loc_reference"
        },
        "connection_type" : {
          "$ref" : "#/definitions/connection_type"
        },
        "ftl_ship_effect" : {
          "$ref" : "../core.yaml#/definitions/assert_reference"
        },
        "ftl_bypass_effect" : {
          "$ref" : "../core.yaml#/definitions/assert_reference"
        },
        "bypass_effect" : {
          "$ref" : "../core.yaml#/definitions/assert_reference"
        },
        "animation_time" : {
          "$ref" : "../core.yaml#/definitions/int"
        },
        "prerequisites" : {
          "type" : "array",
          "items" : {
            "$type" : "tech"
          }
        },
        "on_pre_explore" : {
          "$ref" : "../core.yaml#/definitions/effects"
        },
        "country_can_use" : {
          "$ref" : "../core.yaml#/definitions/triggers"
        },
        "on_action" : {
          "$type" : "on_action"
        },
        "scripted_connection" : {
          "$ref" : "#/definitions/scripted_connection"
        }
      }
    },
    "connection_type" : {
      "type" : "string",
      "enum" : [ "any_other", "one_to_one", "scripted_connection" ]
    },
    "scripted_connection" : {
      "properties" : {
        "nodes" : {
          "$ref" : "../core.yaml#/definitions/triggers"
        },
        "nexus" : {
          "$ref" : "../core.yaml#/definitions/triggers"
        }
      }
    }
  },
  "type" : "object",
  "additionalProperties" : {
    "$ref" : "#/definitions/bypass"
  }
}